pyrunner.py
pyrunner-0.1.4.dist-info/METADATA
pyrunner-0.1.4.dist-info/RECORD
pyrunner-0.1.4.dist-info/WHEEL
pyrunner-0.1.4.dist-info/entry_points.txt
pyrunner-0.1.4.dist-info/top_level.txt
