Metadata-Version: 2.1
Name: pyrunner
Version: 0.1.4
Summary: Wrap your scripts around a cli.
Home-page: https://github.com/cdancette/pyrunner
Author: Corentin Dancette
Author-email: contact@cdancette.fr
License: MIT
Platform: UNKNOWN
Classifier: License :: OSI Approved :: MIT License
Classifier: Programming Language :: Python
Classifier: Programming Language :: Python :: 3
Classifier: Programming Language :: Python :: 3.6
Classifier: Programming Language :: Python :: Implementation :: CPython
Classifier: Programming Language :: Python :: Implementation :: PyPy
Requires-Python: >=3.6.0
